[
  { "id": 1, "name": "ｼﾛ" },
  { "id": 2, "name": "Pﾎﾜｲﾄ" },
  { "id": 3, "name": "ﾍﾞｰｼﾞｭ" },
  { "id": 4, "name": "ｼﾙﾊﾞｰ" },
  { "id": 5, "name": "ｸﾞﾚｰ" },
  { "id": 6, "name": "ｶﾞﾝM" },
  { "id": 7, "name": "ｸﾛ" },
  { "id": 8, "name": "ﾋﾟﾝｸ" },
  { "id": 9, "name": "ﾑﾗｻｷ" },
  { "id": 10, "name": "Wﾚｯﾄﾞ" },
  { "id": 11, "name": "ｱｶ" },
  { "id": 12, "name": "ｷｲﾛ" },
  { "id": 13, "name": "ｵﾚﾝｼﾞ" },
  { "id": 14, "name": "ｺﾞｰﾙﾄﾞ" },
  { "id": 15, "name": "ﾁｬｲﾛ" },
  { "id": 16, "name": "ﾐｽﾞｲﾛ" },
  { "id": 17, "name": "ｱｵ" },
  { "id": 18, "name": "ｺﾝ" },
  { "id": 19, "name": "ｸﾞﾘｰﾝ" },
  { "id": 20, "name": "ﾏｼﾞｮｰﾗ" },
  { "id": 21, "name": "ｿﾉﾀ" }
]
